tecount/__init__.py
tecount/main.py
tecount-1.0.1.dist-info/LICENSE
tecount-1.0.1.dist-info/METADATA
tecount-1.0.1.dist-info/WHEEL
tecount-1.0.1.dist-info/entry_points.txt
tecount-1.0.1.dist-info/top_level.txt
tecount-1.0.1.dist-info/RECORD
