Metadata-Version: 2.1
Name: tecount
Version: 1.0.1
Summary: Count read alignments on transposable elements subfamilies, families and classes.
Home-page: https://github.com/bodegalab/tecount
Author: Benedetto Polimeni
Project-URL: Bug Tracker, https://github.com/bodegalab/tecount/issues
Classifier: Programming Language :: Python :: 3
Classifier: License :: OSI Approved :: MIT License
Classifier: Operating System :: OS Independent
Requires-Python: >=3.7
License-File: LICENSE
Requires-Dist: pysam (>=0.16.0.1)
